README.md
setup.py
PyFriday/__init__.py
PyFriday.egg-info/PKG-INFO
PyFriday.egg-info/SOURCES.txt
PyFriday.egg-info/dependency_links.txt
PyFriday.egg-info/entry_points.txt
PyFriday.egg-info/requires.txt
PyFriday.egg-info/top_level.txt