Metadata-Version: 2.1
Name: PyFriday
Version: 1.1
Summary: A Virtual Assistant In Pure Python..
Home-page: https://github.com/BLUE-DEVIL1134/PyFriday
Author: Akash Pattnaik
Author-email: akashpattnaik.github@gmail.com
License: MIT
Platform: UNKNOWN
Classifier: License :: OSI Approved :: MIT License
Classifier: Programming Language :: Python :: 3.5
Classifier: Programming Language :: Python :: 3.6
Classifier: Programming Language :: Python :: 3.7
Classifier: Programming Language :: Python :: 3.8
Classifier: Operating System :: Microsoft :: Windows
